waste_uploader/__init__.py
waste_uploader/__main__.py
waste_uploader/data/__init__.py
waste_uploader/data/bundle.py
waste_uploader-0.1.5.dist-info/LICENSE.txt
waste_uploader-0.1.5.dist-info/METADATA
waste_uploader-0.1.5.dist-info/WHEEL
waste_uploader-0.1.5.dist-info/entry_points.txt
waste_uploader-0.1.5.dist-info/top_level.txt
waste_uploader-0.1.5.dist-info/RECORD
