Metadata-Version: 2.1
Name: waste-uploader
Version: 0.1.5
Summary: Upload script
Home-page: https://github.com/pypa/sampleproject
Author: Roman Dymov
Author-email: r.dymov@mpgames.rocks
License: UNKNOWN
Platform: UNKNOWN
Classifier: Programming Language :: Python :: 3
Requires-Python: >=3.7
Requires-Dist: awscli (>=1.18.31)
Requires-Dist: requests (==2.23.0)
Requires-Dist: aws-requests-auth (>=0.4.3)
Requires-Dist: marshmallow (>=3.8.0)
